qdeepsdk/__init__.py
qdeepsdk/solver.py
qdeepsdk-1.0.1.dist-info/METADATA
qdeepsdk-1.0.1.dist-info/WHEEL
qdeepsdk-1.0.1.dist-info/top_level.txt
qdeepsdk-1.0.1.dist-info/RECORD
