Metadata-Version: 2.4
Name: qdeepsdk
Version: 1.0.1
Summary: Our hybrid solver for QUBO problems merges classical and quantum computing, efficiently solving complex optimization tasks. It offers fast, accurate results for applications in logistics, finance, and more.
Author: Ahmad Sarhan
Author-email: ahmadhasansarhana@gmail.com
Classifier: Programming Language :: Python :: 3
Classifier: License :: OSI Approved :: MIT License
Classifier: Development Status :: 3 - Alpha
Classifier: Intended Audience :: Developers
Classifier: Topic :: Scientific/Engineering :: Mathematics
Requires-Python: >=3.7
Requires-Dist: numpy>=1.18.0
Requires-Dist: requests>=2.24.0
Dynamic: author
Dynamic: author-email
Dynamic: classifier
Dynamic: description
Dynamic: description-content-type
Dynamic: requires-dist
Dynamic: requires-python
Dynamic: summary
